dirx/__init__.py
dirx/cli/__init__.py
dirx/cli/app/__init__.py
dirx/console.py
dirx/constants.py
dirx/gui/__init__.py
dirx/settings.py
dirx-0.3.0.dist-info/LICENSE
dirx-0.3.0.dist-info/METADATA
dirx-0.3.0.dist-info/WHEEL
dirx-0.3.0.dist-info/entry_points.txt
dirx-0.3.0.dist-info/RECORD
