Metadata-Version: 2.1
Name: dirx
Version: 0.3.0
Summary: 
Home-page: https://github.com/alexisbeaulieu97/dirx
License: MIT
Author: Alexis Beaulieu
Author-email: alexisbeaulieu@protonmail.com
Requires-Python: >=3.11,<4.0
Classifier: License :: OSI Approved :: MIT License
Classifier: Programming Language :: Python :: 3
Classifier: Programming Language :: Python :: 3.11
Requires-Dist: pydantic (>=2.3.0,<3.0.0)
Requires-Dist: pydantic-settings (>=2.0.3,<3.0.0)
Requires-Dist: typer[all] (>=0.9.0,<0.10.0)
Requires-Dist: watchdog (>=3.0.0,<4.0.0)
Project-URL: Repository, https://github.com/alexisbeaulieu97/dirx
